k1s/__init__.py
k1s/autoscale.py
k1s/docker-compose.yml
k1s/dockerautoscaleup.py
k1s/improveauto.py
k1s/httpd/Dockerfile
k1s/httpd/my-httpd.conf
swautoscale-0.2.0.dist-info/METADATA
swautoscale-0.2.0.dist-info/WHEEL
swautoscale-0.2.0.dist-info/entry_points.txt
swautoscale-0.2.0.dist-info/top_level.txt
swautoscale-0.2.0.dist-info/RECORD
