Metadata-Version: 2.1
Name: swautoscale
Version: 0.2.0
Summary: Default template for PDM package
Author-email: GITSangWoo <dogcenta@gmail.com>
License: MIT
Requires-Python: ==3.11.*
Requires-Dist: requests>=2.32.3
Requires-Dist: pytz>=2024.2
Requires-Dist: PyYAML>=6.0.2
